README.rst
setup.py
./LICENSE
./__init__.py
./__main__.py
./browser.py
./server.py
./vnc.py
.ruamel/__init__.py
.ruamel/browser/__init__.py
ruamel.browser.server.egg-info/PKG-INFO
ruamel.browser.server.egg-info/SOURCES.txt
ruamel.browser.server.egg-info/dependency_links.txt
ruamel.browser.server.egg-info/entry_points.txt
ruamel.browser.server.egg-info/namespace_packages.txt
ruamel.browser.server.egg-info/requires.txt
ruamel.browser.server.egg-info/top_level.txt